[
    {
        "patientId"  : "1", 
        "name"       : "Marianne J. Lee",
        "age"        : "64",
        "height"     : "172",
        "weight"     : "84",
        "bmi"        : "26.85",
        "birthday"   : "Jul 16, 1953",       
        "gender"     : "female",
        "injury"     : "Collar bone",
        "imgUrl"     : "img/patient2.jpg",
        "admission"  : "Mar 20, 2015",
        "recovery"   : "20",
        "bookmark"   : "none",
        "status"     : "incomplete",
        "totalSessions" : "40",
        "CompletedSessions" : "24"
    }
]